LICENSE.txt
MANIFEST.in
README.md
README.rst
setup.cfg
setup.py
yarlp/__init__.py
yarlp.egg-info/PKG-INFO
yarlp.egg-info/SOURCES.txt
yarlp.egg-info/dependency_links.txt
yarlp.egg-info/entry_points.txt
yarlp.egg-info/requires.txt
yarlp.egg-info/top_level.txt
yarlp/agent/__init__.py
yarlp/agent/a2c_agent.py
yarlp/agent/base_agent.py
yarlp/agent/baseline_agents.py
yarlp/agent/cem_agent.py
yarlp/agent/ddqn_agent.py
yarlp/agent/pg_agents.py
yarlp/agent/trpo_agent.py
yarlp/experiment/__init__.py
yarlp/experiment/benchmarks.py
yarlp/experiment/experiment.py
yarlp/experiment/experiment_schema.py
yarlp/experiment/job.py
yarlp/experiment/plotting.py
yarlp/external/__init__.py
yarlp/external/baselines/__init__.py
yarlp/external/baselines/setup.py
yarlp/external/baselines/baselines/__init__.py
yarlp/external/baselines/baselines/logger.py
yarlp/external/baselines/baselines/results_plotter.py
yarlp/external/baselines/baselines/a2c/__init__.py
yarlp/external/baselines/baselines/a2c/a2c.py
yarlp/external/baselines/baselines/a2c/policies.py
yarlp/external/baselines/baselines/a2c/run_atari.py
yarlp/external/baselines/baselines/a2c/utils.py
yarlp/external/baselines/baselines/acer/__init__.py
yarlp/external/baselines/baselines/acer/acer_simple.py
yarlp/external/baselines/baselines/acer/buffer.py
yarlp/external/baselines/baselines/acer/policies.py
yarlp/external/baselines/baselines/acer/run_atari.py
yarlp/external/baselines/baselines/acktr/__init__.py
yarlp/external/baselines/baselines/acktr/acktr_cont.py
yarlp/external/baselines/baselines/acktr/acktr_disc.py
yarlp/external/baselines/baselines/acktr/filters.py
yarlp/external/baselines/baselines/acktr/kfac.py
yarlp/external/baselines/baselines/acktr/kfac_utils.py
yarlp/external/baselines/baselines/acktr/policies.py
yarlp/external/baselines/baselines/acktr/run_atari.py
yarlp/external/baselines/baselines/acktr/run_mujoco.py
yarlp/external/baselines/baselines/acktr/running_stat.py
yarlp/external/baselines/baselines/acktr/utils.py
yarlp/external/baselines/baselines/acktr/value_functions.py
yarlp/external/baselines/baselines/bench/__init__.py
yarlp/external/baselines/baselines/bench/benchmarks.py
