Metadata-Version: 1.0
Name: yarlp
Version: 0.1.0
Summary: yarlp
Home-page: https://github.com/btaba/yarlp
Author: Baruch Tabanpour
Author-email: baruch@tabanpour.info
License: MIT
Keywords: reinforcement learning,deep reinforcement learning,experiment,benchmark
Platform: UNKNOWN
